bahasamanis.py
bahasamanis_cli.py
bahasamanis_data/__init__.py
bahasamanis_data/bm_standar/acak.bm
bahasamanis_data/bm_standar/berkas.bm
bahasamanis_data/bm_standar/jaringan.bm
bahasamanis_data/bm_standar/json.bm
bahasamanis_data/bm_standar/waktu.bm
bahasamanis-0.1.11.post1.dist-info/METADATA
bahasamanis-0.1.11.post1.dist-info/WHEEL
bahasamanis-0.1.11.post1.dist-info/entry_points.txt
bahasamanis-0.1.11.post1.dist-info/top_level.txt
bahasamanis-0.1.11.post1.dist-info/RECORD
