Metadata-Version: 2.4
Name: bahasamanis
Version: 0.1.11.post1
Summary: Bahasa Manis (BM): Bahasa pemrograman berbahasa Indonesia dengan interpreter, transpiler, dan playground.
Author: M. Samjaya
License: MIT
Project-URL: Homepage, https://github.com/TheCoderScients/bahasamanis
Project-URL: Repository, https://github.com/TheCoderScients/bahasamanis
Keywords: bahasa manis,indonesian,language,interpreter,transpiler
Classifier: Programming Language :: Python :: 3
Classifier: License :: OSI Approved :: MIT License
Classifier: Operating System :: OS Independent
Requires-Python: >=3.9
